maktaba/__init__.py
maktaba/config.py
maktaba/exceptions.py
maktaba/logging.py
maktaba/models.py
maktaba/version.py
maktaba/chunking/__init__.py
maktaba/chunking/base.py
maktaba/chunking/llamaindex.py
maktaba/chunking/models.py
maktaba/chunking/simple.py
maktaba/chunking/unstructured.py
maktaba/citation/__init__.py
maktaba/citation/formatter.py
maktaba/embedding/__init__.py
maktaba/embedding/azure.py
maktaba/embedding/base.py
maktaba/embedding/cohere.py
maktaba/embedding/openai.py
maktaba/embedding/voyage.py
maktaba/keyword/__init__.py
maktaba/keyword/base.py
maktaba/keyword/qdrant.py
maktaba/keyword/supabase.py
maktaba/llm/__init__.py
maktaba/llm/base.py
maktaba/llm/openai.py
maktaba/llm/prompts.py
maktaba/pipeline/__init__.py
maktaba/pipeline/agentic.py
maktaba/pipeline/ingestion.py
maktaba/pipeline/query.py
maktaba/pipeline/deep_research/__init__.py
maktaba/pipeline/deep_research/config.py
maktaba/pipeline/deep_research/models.py
maktaba/pipeline/deep_research/pipeline.py
maktaba/pipeline/deep_research/prompts.py
maktaba/reranking/__init__.py
maktaba/reranking/base.py
maktaba/reranking/cohere.py
maktaba/reranking/cross_encoder.py
maktaba/reranking/zeroentropy.py
maktaba/retrieval/__init__.py
maktaba/retrieval/hybrid.py
maktaba/retrieval/query_condenser.py
maktaba/retrieval/vector.py
maktaba/storage/__init__.py
maktaba/storage/base.py
maktaba/storage/chroma.py
maktaba/storage/pinecone.py
maktaba/storage/qdrant.py
maktaba/storage/weaviate.py
maktaba-0.1.20.dist-info/METADATA
maktaba-0.1.20.dist-info/WHEEL
maktaba-0.1.20.dist-info/licenses/LICENSE
maktaba-0.1.20.dist-info/RECORD
