Metadata-Version: 2.4
Name: maktaba
Version: 0.1.20
Summary: Production-ready RAG infrastructure for multilingual applications
Project-URL: Homepage, https://github.com/nuhatech/maktaba
Project-URL: Documentation, https://maktaba.nuhatech.com
Project-URL: Repository, https://github.com/nuhatech/maktaba
Project-URL: Issues, https://github.com/nuhatech/maktaba/issues
Author-email: NuhaTech <contact@nuhatech.com>
License: MIT
License-File: LICENSE
Keywords: ai,embeddings,llm,rag,retrieval,vector-search
Classifier: Development Status :: 3 - Alpha
Classifier: Intended Audience :: Developers
Classifier: License :: OSI Approved :: MIT License
Classifier: Programming Language :: Python :: 3
Classifier: Programming Language :: Python :: 3.10
Classifier: Programming Language :: Python :: 3.11
Classifier: Programming Language :: Python :: 3.12
Requires-Python: >=3.10
Requires-Dist: httpx>=0.27
Requires-Dist: pydantic-settings>=2.0
Requires-Dist: pydantic>=2.0
Requires-Dist: tenacity>=8.0
Provides-Extra: all
Requires-Dist: azure-ai-inference>=1.0.0b9; extra == 'all'
Requires-Dist: chromadb<1.1,>=0.4; extra == 'all'
Requires-Dist: cohere>=5.0; extra == 'all'
Requires-Dist: llama-index-core>=0.12; extra == 'all'
Requires-Dist: llama-index-readers-file>=0.4; extra == 'all'
Requires-Dist: openai>=1.0; extra == 'all'
Requires-Dist: pinecone-client>=3.0; extra == 'all'
Requires-Dist: python-magic>=0.4; extra == 'all'
Requires-Dist: qdrant-client>=1.11; extra == 'all'
Requires-Dist: redis>=5.0; extra == 'all'
Requires-Dist: supabase>=2.0; extra == 'all'
Requires-Dist: unstructured[all-docs]>=0.16; extra == 'all'
Requires-Dist: voyageai>=0.2; extra == 'all'
Requires-Dist: zeroentropy>=0.1.0a6; extra == 'all'
Provides-Extra: azure
Requires-Dist: azure-ai-inference>=1.0.0b9; extra == 'azure'
Provides-Extra: chroma
Requires-Dist: chromadb<1.1,>=0.4; extra == 'chroma'
Provides-Extra: cohere
Requires-Dist: cohere>=5.0; extra == 'cohere'
Provides-Extra: openai
Requires-Dist: openai>=1.0; extra == 'openai'
Provides-Extra: pinecone
Requires-Dist: pinecone-client>=3.0; extra == 'pinecone'
Provides-Extra: qdrant
Requires-Dist: qdrant-client>=1.11; extra == 'qdrant'
Provides-Extra: redis
Requires-Dist: redis>=5.0; extra == 'redis'
Provides-Extra: supabase
Requires-Dist: supabase>=2.0; extra == 'supabase'
Provides-Extra: unstructured
Requires-Dist: llama-index-core>=0.12; extra == 'unstructured'
Requires-Dist: llama-index-readers-file>=0.4; extra == 'unstructured'
Requires-Dist: python-magic-bin>=0.4; (platform_system == 'Windows') and extra == 'unstructured'
Requires-Dist: python-magic>=0.4; (platform_system != 'Windows') and extra == 'unstructured'
Requires-Dist: unstructured[all-docs]>=0.16; extra == 'unstructured'
Provides-Extra: unstructured-minimal
Requires-Dist: llama-index-core>=0.12; extra == 'unstructured-minimal'
Requires-Dist: llama-index-readers-file>=0.4; extra == 'unstructured-minimal'
Requires-Dist: unstructured>=0.16; extra == 'unstructured-minimal'
Provides-Extra: voyage
Requires-Dist: voyageai>=0.2; extra == 'voyage'
Provides-Extra: zeroentropy
Requires-Dist: zeroentropy>=0.1.0a6; extra == 'zeroentropy'
